mpl_fill_cmap_between.py
mpl_fill_cmap_between-0.3.1.dist-info/WHEEL
mpl_fill_cmap_between-0.3.1.dist-info/METADATA
mpl_fill_cmap_between-0.3.1.dist-info/RECORD
