Metadata-Version: 2.1
Name: mpl-fill-cmap-between
Version: 0.3.1
Summary: Create fillbetween plots filled with any colormap
Home-page: https://github.com/cristobaltapia/mpl_fill_cmap_between
License: MIT
Keywords: matplotlib,fill_between
Author: Cristóbal Tapia Camú
Author-email: crtapia@gmail.com
Requires-Python: >=3.8,<4.0
Classifier: License :: OSI Approved :: MIT License
Classifier: Programming Language :: Python :: 3
Classifier: Programming Language :: Python :: 3.8
Classifier: Programming Language :: Python :: 3.9
Classifier: Programming Language :: Python :: 3.10
Classifier: Programming Language :: Python :: 3.11
Requires-Dist: matplotlib (>=3.0.0,<4.0.0)
Project-URL: Repository, https://github.com/cristobaltapia/mpl_fill_cmap_between
